hi_gitsangwoo/__init__.py
hi_gitsangwoo/hello.py
hi_GITSangWoo-0.8.0.dist-info/METADATA
hi_GITSangWoo-0.8.0.dist-info/WHEEL
hi_GITSangWoo-0.8.0.dist-info/entry_points.txt
hi_GITSangWoo-0.8.0.dist-info/top_level.txt
hi_GITSangWoo-0.8.0.dist-info/RECORD
