Metadata-Version: 2.1
Name: hi_GITSangWoo
Version: 0.8.0
Summary: Default template for PDM package
Author-email: GITSangWoo <dogcenta@gmail.com>
License: MIT
Requires-Python: ==3.12.*
